{
  "title": "ক্যারিয়ার",
  "description": "বর্তমান চাকরির সুযোগগুলো দেখুন এবং আমাদের মানবিক মিশনে যুক্ত হন।",
  "meta_img": "",
  "jobs": [
    {
      "title": "UI/UX ও প্রোডাক্ট ডিজাইনার",
      "experience": "২ বছর",
      "type": "ফুলটাইম",
      "location": "১৭২৭ এলিফ্যান্ট রোড, ব্লক-ডি, ঢাকা",
      "button": "বিস্তারিত",
      "url": "/connect/career/ui-ux-product-designer-1"
    },
    {
      "title": "UI/UX ও প্রোডাক্ট ডিজাইনার",
      "experience": "২ বছর",
      "type": "ফুলটাইম",
      "location": "১৭২৭ এলিফ্যান্ট রোড, ব্লক-ডি, ঢাকা",
      "button": "বিস্তারিত",
      "url": "/connect/career/ui-ux-product-designer-2"
    },
    {
      "title": "UI/UX ও প্রোডাক্ট ডিজাইনার",
      "experience": "২ বছর",
      "type": "ফুলটাইম",
      "location": "১৭২৭ এলিফ্যান্ট রোড, ব্লক-ডি, ঢাকা",
      "button": "বিস্তারিত",
      "url": "/connect/career/ui-ux-product-designer-3"
    },
    {
      "title": "UI/UX ও প্রোডাক্ট ডিজাইনার",
      "experience": "২ বছর",
      "type": "ফুলটাইম",
      "location": "১৭২৭ এলিফ্যান্ট রোড, ব্লক-ডি, ঢাকা",
      "button": "বিস্তারিত",
      "url": "/connect/career/ui-ux-product-designer-4"
    },
    {
      "title": "UI/UX ও প্রোডাক্ট ডিজাইনার",
      "experience": "২ বছর",
      "type": "ফুলটাইম",
      "location": "১৭২৭ এলিফ্যান্ট রোড, ব্লক-ডি, ঢাকা",
      "button": "বিস্তারিত",
      "url": "/connect/career/ui-ux-product-designer-5"
    },
    {
      "title": "UI/UX ও প্রোডাক্ট ডিজাইনার",
      "experience": "২ বছর",
      "type": "ফুলটাইম",
      "location": "১৭২৭ এলিফ্যান্ট রোড, ব্লক-ডি, ঢাকা",
      "button": "বিস্তারিত",
      "url": "/connect/career/ui-ux-product-designer-6"
    },
    {
      "title": "UI/UX ও প্রোডাক্ট ডিজাইনার",
      "experience": "২ বছর",
      "type": "ফুলটাইম",
      "location": "১৭২৭ এলিফ্যান্ট রোড, ব্লক-ডি, ঢাকা",
      "button": "বিস্তারিত",
      "url": "/connect/career/ui-ux-product-designer-7"
    },
    {
      "title": "UI/UX ও প্রোডাক্ট ডিজাইনার",
      "experience": "২ বছর",
      "type": "ফুলটাইম",
      "location": "১৭২৭ এলিফ্যান্ট রোড, ব্লক-ডি, ঢাকা",
      "button": "বিস্তারিত",
      "url": "/connect/career/ui-ux-product-designer-8"
    }
  ]
}
